[
	{
		"content": "Reprehenderit culpa nisi est dolore sit aliquip est enim velit tempor ipsum."
	},
	{
		"content": "Nostrud aute laboris non sit minim ipsum consectetur cupidatat eu non cillum."
	},
	{ "content": "Mollit ad sunt ut consequat ipsum id consequat." },
	{ "content": "Dolor reprehenderit sint aliqua irure ut fugiat." },
	{
		"content": "Eiusmod dolore adipisicing id velit occaecat ad reprehenderit ut sint nulla laborum."
	},
	{
		"content": "Aliqua sunt do dolore labore nisi cupidatat laborum eiusmod labore aliqua."
	}
]
